<?xml version="1.0" encoding="utf-8"?>
<clothing-items>
 <clothing>
  <id>
   514387225
  </id>
  <name>
   Converse Sweater I-4377
  </name>
  <category>
   Sweater
  </category>
  <size>
   M
  </size>
  <color>
   Красный
  </color>
  <material>
   Кожа
  </material>
  <price>
   240759
  </price>
  <rating>
   3.06
  </rating>
  <reviews>
   308599
  </reviews>
  <exclusive>
   yes
  </exclusive>
  <sporty>
   yes
  </sporty>
 </clothing>
 <clothing>
  <id>
   731888245
  </id>
  <name>
   Asics Pants F-8311
  </name>
  <category>
   Pants
  </category>
  <size>
   S
  </size>
  <color>
   Синий
  </color>
  <material>
   Вискоза
  </material>
  <price>
   980520
  </price>
  <rating>
   1.37
  </rating>
  <reviews>
   463562
  </reviews>
  <exclusive>
   no
  </exclusive>
  <sporty>
   no
  </sporty>
 </clothing>
 <clothing>
  <id>
   565197965
  </id>
  <name>
   DC Hat O-4861
  </name>
  <category>
   Hat
  </category>
  <size>
   XXL
  </size>
  <color>
   Фиолетовый
  </color>
  <material>
   Нейлон
  </material>
  <price>
   234028
  </price>
  <rating>
   3.88
  </rating>
  <reviews>
   625079
  </reviews>
  <new>
   +
  </new>
  <sporty>
   yes
  </sporty>
 </clothing>
 <clothing>
  <id>
   444948479
  </id>
  <name>
   Addidas Belts J-1756
  </name>
  <category>
   Belts
  </category>
  <size>
   XXL
  </size>
  <color>
   Красный
  </color>
  <material>
   Шелк
  </material>
  <price>
   300963
  </price>
  <rating>
   2.64
  </rating>
  <reviews>
   102084
  </reviews>
  <new>
   -
  </new>
  <sporty>
   yes
  </sporty>
 </clothing>
 <clothing>
  <id>
   770772726
  </id>
  <name>
   Asics Umbrellas I-6033
  </name>
  <category>
   Umbrellas
  </category>
  <size>
   M
  </size>
  <color>
   Красный
  </color>
  <material>
   Шерсть
  </material>
  <price>
   818276
  </price>
  <rating>
   1.56
  </rating>
  <reviews>
   401785
  </reviews>
  <new>
   +
  </new>
  <exclusive>
   no
  </exclusive>
  <sporty>
   yes
  </sporty>
 </clothing>
 <clothing>
  <id>
   256811043
  </id>
  <name>
   Lacoste Handbags M-2998
  </name>
  <category>
   Handbags
  </category>
  <size>
   S
  </size>
  <color>
   Голубой
  </color>
  <material>
   Кожа
  </material>
  <price>
   941825
  </price>
  <rating>
   2.84
  </rating>
  <reviews>
   68096
  </reviews>
  <exclusive>
   no
  </exclusive>
 </clothing>
 <clothing>
  <id>
   488187777
  </id>
  <name>
   Ellesse Handbags B-7861
  </name>
  <category>
   Handbags
  </category>
  <size>
   L
  </size>
  <color>
   Голубой
  </color>
  <material>
   Хлопок
  </material>
  <price>
   803013
  </price>
  <rating>
   1.11
  </rating>
  <reviews>
   181994
  </reviews>
  <new>
   -
  </new>
  <exclusive>
   no
  </exclusive>
  <sporty>
   yes
  </sporty>
 </clothing>
 <clothing>
  <id>
   378028709
  </id>
  <name>
   Addidas Belts P-6791
  </name>
  <category>
   Belts
  </category>
  <size>
   XL
  </size>
  <color>
   Голубой
  </color>
  <material>
   Полиэстер
  </material>
  <price>
   221287
  </price>
  <rating>
   3.32
  </rating>
  <reviews>
   965550
  </reviews>
  <exclusive>
   yes
  </exclusive>
 </clothing>
 <clothing>
  <id>
   560702129
  </id>
  <name>
   Addidas Sweater V-2025
  </name>
  <category>
   Sweater
  </category>
  <size>
   S
  </size>
  <color>
   Красный
  </color>
  <material>
   Вискоза
  </material>
  <price>
   363441
  </price>
  <rating>
   3.66
  </rating>
  <reviews>
   788357
  </reviews>
  <exclusive>
   no
  </exclusive>
  <sporty>
   yes
  </sporty>
 </clothing>
 <clothing>
  <id>
   995106019
  </id>
  <name>
   Under Armour Umbrellas L-4499
  </name>
  <category>
   Umbrellas
  </category>
  <size>
   M
  </size>
  <color>
   Зеленый
  </color>
  <material>
   Вискоза
  </material>
  <price>
   761586
  </price>
  <rating>
   1.37
  </rating>
  <reviews>
   350365
  </reviews>
  <new>
   -
  </new>
  <exclusive>
   no
  </exclusive>
  <sporty>
   no
  </sporty>
 </clothing>
 <clothing>
  <id>
   242960690
  </id>
  <name>
   DC Dress N-8700
  </name>
  <category>
   Dress
  </category>
  <size>
   XXL
  </size>
  <color>
   Фиолетовый
  </color>
  <material>
   Лен
  </material>
  <price>
   101292
  </price>
  <rating>
   4.98
  </rating>
  <reviews>
   729828
  </reviews>
  <new>
   +
  </new>
  <sporty>
   yes
  </sporty>
 </clothing>
 <clothing>
  <id>
   132357865
  </id>
  <name>
   Vans Handbags V-4146
  </name>
  <category>
   Handbags
  </category>
  <size>
   M
  </size>
  <color>
   Оранжевый
  </color>
  <material>
   Лен
  </material>
  <price>
   678415
  </price>
  <rating>
   3.66
  </rating>
  <reviews>
   380724
  </reviews>
  <new>
   -
  </new>
  <exclusive>
   yes
  </exclusive>
 </clothing>
 <clothing>
  <id>
   938331074
  </id>
  <name>
   Under Armour Shoes E-3689
  </name>
  <category>
   Shoes
  </category>
  <size>
   XXL
  </size>
  <color>
   Фиолетовый
  </color>
  <material>
   Шерсть
  </material>
  <price>
   814249
  </price>
  <rating>
   1.64
  </rating>
  <reviews>
   851385
  </reviews>
  <new>
   +
  </new>
  <exclusive>
   no
  </exclusive>
 </clothing>
 <clothing>
  <id>
   280246790
  </id>
  <name>
   Reebok Pants Y-6222
  </name>
  <category>
   Pants
  </category>
  <size>
   S
  </size>
  <color>
   Желтый
  </color>
  <material>
   Вискоза
  </material>
  <price>
   890625
  </price>
  <rating>
   3.4
  </rating>
  <reviews>
   655714
  </reviews>
  <new>
   +
  </new>
  <exclusive>
   no
  </exclusive>
  <sporty>
   no
  </sporty>
 </clothing>
 <clothing>
  <id>
   129467669
  </id>
  <name>
   Lacoste Pants L-7138
  </name>
  <category>
   Pants
  </category>
  <size>
   XL
  </size>
  <color>
   Желтый
  </color>
  <material>
   Хлопок
  </material>
  <price>
   399162
  </price>
  <rating>
   2.82
  </rating>
  <reviews>
   455571
  </reviews>
  <exclusive>
   no
  </exclusive>
 </clothing>
</clothing-items>
